README.rst
setup.py
slbsl.py
slbsl.egg-info/PKG-INFO
slbsl.egg-info/SOURCES.txt
slbsl.egg-info/dependency_links.txt
slbsl.egg-info/entry_points.txt
slbsl.egg-info/pbr.json
slbsl.egg-info/requires.txt
slbsl.egg-info/top_level.txt