Metadata-Version: 1.0
Name: slbsl
Version: 0.2.3
Summary: Convert paths from Windows to UNIX and vice versa.
Home-page: https://github.com/cb109/slbsl.git
Author: Christoph Buelter
Author-email: info@cbuelter.de
License: UNKNOWN
Keywords: slash,backslash,linux,unix,windows,conversion
Platform: UNKNOWN
